gaarf_exporter/__init__.py
gaarf_exporter/collector.py
gaarf_exporter/exceptions.py
gaarf_exporter/exporter.py
gaarf_exporter/exporter_service.py
gaarf_exporter/main.py
gaarf_exporter/registry.py
gaarf_exporter/util.py
gaarf_exporter/collector_definitions/__init__.py
gaarf_exporter/collector_definitions/disapprovals.yaml
gaarf_exporter/collector_definitions/mapping.yaml
gaarf_exporter/collector_definitions/misc.yaml
gaarf_exporter/collector_definitions/performance.yaml
gaarf_exporter-1.2.1.dist-info/METADATA
gaarf_exporter-1.2.1.dist-info/WHEEL
gaarf_exporter-1.2.1.dist-info/entry_points.txt
gaarf_exporter-1.2.1.dist-info/top_level.txt
gaarf_exporter-1.2.1.dist-info/RECORD
