Metadata-Version: 2.4
Name: gaarf-exporter
Version: 1.2.1
Summary: Prometheus exporter for Google Ads.
Author-email: "Google Inc. (gTech gPS CSE team)" <no-reply@google.com>
License: Apache 2.0
Classifier: Programming Language :: Python :: 3 :: Only
Classifier: Programming Language :: Python :: 3.9
Classifier: Programming Language :: Python :: 3.10
Classifier: Programming Language :: Python :: 3.11
Classifier: Programming Language :: Python :: 3.12
Classifier: Programming Language :: Python :: 3.13
Classifier: Intended Audience :: Developers
Classifier: Topic :: Software Development :: Libraries :: Python Modules
Classifier: Operating System :: OS Independent
Classifier: License :: OSI Approved :: Apache Software License
Requires-Python: >=3.9
Requires-Dist: prometheus-client
Requires-Dist: google-ads-api-report-fetcher
Requires-Dist: fastapi
Requires-Dist: uvicorn
Requires-Dist: pydantic
Requires-Dist: eval-type-backport
